avocados/__init__.py
avocados/asgi.py
avocados/serializers.py
avocados/settings.py
avocados/urls.py
avocados/views.py
avocados/wsgi.py
avocados-0.1.0.dist-info/METADATA
avocados-0.1.0.dist-info/WHEEL
avocados-0.1.0.dist-info/top_level.txt
avocados-0.1.0.dist-info/RECORD
