Metadata-Version: 2.1
Name: avocados
Version: 0.1.0
Summary: UNKNOWN
Home-page: UNKNOWN
Author: UNKNOWN
Author-email: UNKNOWN
License: UNKNOWN
Platform: UNKNOWN
Requires-Dist: django
Requires-Dist: djangorestframework
Requires-Dist: pygments
Requires-Dist: pytest
